opentelemetry/exporter/jaeger/py.typed
opentelemetry/exporter/jaeger/version.py
opentelemetry_exporter_jaeger-1.19.0.dist-info/METADATA
opentelemetry_exporter_jaeger-1.19.0.dist-info/WHEEL
opentelemetry_exporter_jaeger-1.19.0.dist-info/entry_points.txt
opentelemetry_exporter_jaeger-1.19.0.dist-info/licenses/LICENSE
opentelemetry_exporter_jaeger-1.19.0.dist-info/RECORD
